utdg_env/__init__.py
utdg_env/__version__.py
utdg_env/callbacks/__init__.py
utdg_env/callbacks/curriculum_callback.py
utdg_env/callbacks/hf_upload_callback.py
utdg_env/callbacks/save_model_callback.py
utdg_env/callbacks/ui_stats_callback.py
utdg_env/callbacks/wandb_callback.py
utdg_env/configs/__init__.py
utdg_env/configs/config_schema.py
utdg_env/configs/default.yaml
utdg_env/configs/agent/__init__.py
utdg_env/configs/agent/maskable_ppo.yaml
utdg_env/configs/callbacks/hf_upload.yaml
utdg_env/configs/callbacks/wandb.yaml
utdg_env/configs/checkpoint/default.yaml
utdg_env/configs/env/__init__.py
utdg_env/configs/env/default.yaml
utdg_env/configs/evaluation/default.yaml
utdg_env/configs/model/default.yaml
utdg_env/configs/model/ppo.yaml
utdg_env/configs/runtime/__init__.py
utdg_env/configs/runtime/native.yaml
utdg_env/configs/runtime/web-hf-demo.yaml
utdg_env/configs/runtime/web-hf-train.yaml
utdg_env/configs/runtime/web-local.yaml
utdg_env/configs/sweeps/sweep.yaml
utdg_env/configs/training/default.yaml
utdg_env/env/__init__.py
utdg_env/env/base_env.py
utdg_env/env/registry.py
utdg_env/experiment/__init__.py
utdg_env/experiment/manager.py
utdg_env/experiment/model_card.py
utdg_env/experiment/utils.py
utdg_env/launcher/__init__.py
utdg_env/launcher/godot_launcher.py
utdg_env/transport/__init__.py
utdg_env/transport/__main__.py
utdg_env/transport/protocol.py
utdg_env/transport/transport_base.py
utdg_env/transport/transport_hf.py
utdg_env/transport/transport_native.py
utdg_env/transport/transport_web.py
utdg_env/utils/__init__.py
utdg_env/utils/hydra_loader.py
utdg_env/utils/runtime_modes.py
utdg_env-0.3.0.dist-info/METADATA
utdg_env-0.3.0.dist-info/WHEEL
utdg_env-0.3.0.dist-info/top_level.txt
utdg_env-0.3.0.dist-info/RECORD
