Metadata-Version: 2.4
Name: utdg-env
Version: 0.3.0
Summary: Gymnasium environment for Untitled Tower Defense Game
Author-email: chrisjcc <your.email@example.com>
License-Expression: MIT
Project-URL: Homepage, https://github.com/chrisjcc/UTDG
Project-URL: Bug Tracker, https://github.com/chrisjcc/UTDG/issues
Requires-Python: >=3.8
Requires-Dist: gymnasium>=1.0.0
Requires-Dist: numpy>=1.21.0
Requires-Dist: websockets>=10.0
Requires-Dist: hydra-core>=1.3.0
Requires-Dist: omegaconf>=2.3.0
Provides-Extra: train
Requires-Dist: stable-baselines3>=2.0.0; extra == "train"
Requires-Dist: sb3-contrib>=2.0.0; extra == "train"
Requires-Dist: tensorboard>=2.10.0; extra == "train"
Requires-Dist: playwright>=1.40.0; extra == "train"
Provides-Extra: dev
Requires-Dist: pytest>=7.0.0; extra == "dev"
Requires-Dist: pytest-cov>=4.0.0; extra == "dev"
Requires-Dist: black>=22.0.0; extra == "dev"
Requires-Dist: ruff>=0.1.0; extra == "dev"
Requires-Dist: mypy>=0.991; extra == "dev"
